{
  "starting_equity": 93637,
  "ending_equity": 77658.66,
  "total_return_pct": -17.06,
  "net_pnl": -15978.34,
  "sharpe_ratio": -0.17,
  "profit_factor": 0.95,
  "max_drawdown_pct": 43.59,
  "max_drawdown_dollar": 53201.0,
  "total_trades": 559,
  "win_rate_pct": 40.6,
  "avg_win": 1479.97,
  "avg_loss": -1060.04,
  "avg_r_multiple": 0.0,
  "monthly_pnl": {
    "2025-02": 18244.21,
    "2025-03": -5532.52,
    "2025-04": -15450.34,
    "2025-05": -10769.85,
    "2025-06": 4343.03,
    "2025-07": 1023.38,
    "2025-08": -10665.45,
    "2025-09": -4756.39,
    "2025-10": 12081.68,
    "2025-11": -2180.25,
    "2025-12": -270.94,
    "2026-01": -2044.91
  },
  "top_symbols": {
    "GSAT": 9315.68,
    "TSLA": 7279.92,
    "AVGO": 7165.43,
    "MU": 6318.29,
    "MRVL": 6050.29,
    "NVDA": 5693.05,
    "SMCI": 4909.07,
    "JPM": 4384.78,
    "AMZN": 4004.86,
    "HUT": 3664.3
  },
  "trades": [
    {
      "date": "2026-01-16",
      "symbol": "V",
      "signal": "long",
      "entry": 327.59,
      "shares": 1595,
      "pnl": 1149.18,
      "r_multiple": 0.53,
      "risk_pct": 0.03,
      "regime": "aggressive_bull",
      "vix": 15.9
    },
    {
      "date": "2026-01-16",
      "symbol": "MA",
      "signal": "long",
      "entry": 542.37,
      "shares": 315,
      "pnl": -721.51,
      "r_multiple": -1.0,
      "risk_pct": 0.01,
      "regime": "aggressive_bull",
      "vix": 15.9
    },
    {
      "date": "2026-01-16",
      "symbol": "AFRM",
      "signal": "long",
      "entry": 74.58,
      "shares": 556,
      "pnl": 96.4,
      "r_multiple": 0.13,
      "risk_pct": 0.01,
      "regime": "aggressive_bull",
      "vix": 15.9
    },
    {
      "date": "2026-01-16",
      "symbol": "JPM",
      "signal": "long",
      "entry": 311.99,
      "shares": 584,
      "pnl": 2168.1,
      "r_multiple": 3.0,
      "risk_pct": 0.01,
      "regime": "aggressive_bull",
      "vix": 15.9
    },
    {
      "date": "2026-01-20",
      "symbol": "V",
      "signal": "long",
      "entry": 324.37,
      "shares": 861,
      "pnl": 1364.05,
      "r_multiple": 0.91,
      "risk_pct": 0.02,
      "regime": "bull",
      "vix": 20.1
    },
    {
      "date": "2026-01-20",
      "symbol": "MA",
      "signal": "long",
      "entry": 534.49,
      "shares": 238,
      "pnl": -749.57,
      "r_multiple": -1.0,
      "risk_pct": 0.01,
      "regime": "bull",
      "vix": 20.1
    },
    {
      "date": "2026-01-20",
      "symbol": "AFRM",
      "signal": "long",
      "entry": 72.55,
      "shares": 698,
      "pnl": -749.69,
      "r_multiple": -1.0,
      "risk_pct": 0.01,
      "regime": "bull",
      "vix": 20.1
    },
    {
      "date": "2026-01-20",
      "symbol": "SMCI",
      "signal": "long",
      "entry": 31.07,
      "shares": 1442,
      "pnl": 508.49,
      "r_multiple": 0.68,
      "risk_pct": 0.01,
      "regime": "bull",
      "vix": 20.1
    },
    {
      "date": "2026-01-20",
      "symbol": "RIOT",
      "signal": "long",
      "entry": 18.33,
      "shares": 2282,
      "pnl": -523.15,
      "r_multiple": -0.7,
      "risk_pct": 0.01,
      "regime": "bull",
      "vix": 20.1
    },
    {
      "date": "2026-01-21",
      "symbol": "SMCI",
      "signal": "long",
      "entry": 31.98,
      "shares": 1868,
      "pnl": -748.05,
      "r_multiple": -1.0,
      "risk_pct": 0.01,
      "regime": "aggressive_bull",
      "vix": 16.9
    },
    {
      "date": "2026-01-22",
      "symbol": "SMCI",
      "signal": "long",
      "entry": 33.24,
      "shares": 1881,
      "pnl": -740.64,
      "r_multiple": -1.0,
      "risk_pct": 0.01,
      "regime": "aggressive_bull",
      "vix": 15.6
    },
    {
      "date": "2026-01-22",
      "symbol": "NFLX",
      "signal": "long",
      "entry": 84.57,
      "shares": 1419,
      "pnl": -740.72,
      "r_multiple": -1.0,
      "risk_pct": 0.01,
      "regime": "aggressive_bull",
      "vix": 15.6
    },
    {
      "date": "2026-01-22",
      "symbol": "LCID",
      "signal": "long",
      "entry": 11.8,
      "shares": 2993,
      "pnl": -740.77,
      "r_multiple": -1.0,
      "risk_pct": 0.01,
      "regime": "aggressive_bull",
      "vix": 15.6
    },
    {
      "date": "2026-01-23",
      "symbol": "RIOT",
      "signal": "long",
      "entry": 16.97,
      "shares": 8260,
      "pnl": 6467.58,
      "r_multiple": 3.0,
      "risk_pct": 0.03,
      "regime": "aggressive_bull",
      "vix": 16.1
    },
    {
      "date": "2026-01-27",
      "symbol": "INTC",
      "signal": "long",
      "entry": 44.04,
      "shares": 1349,
      "pnl": -121.75,
      "r_multiple": -0.16,
      "risk_pct": 0.01,
      "regime": "aggressive_bull",
      "vix": 16.4
    },
    {
      "date": "2026-01-27",
      "symbol": "LCID",
      "signal": "long",
      "entry": 10.76,
      "shares": 6002,
      "pnl": 1348.95,
      "r_multiple": 1.72,
      "risk_pct": 0.01,
      "regime": "aggressive_bull",
      "vix": 16.4
    },
    {
      "date": "2026-01-27",
      "symbol": "ARM",
      "signal": "long",
      "entry": 116.52,
      "shares": 551,
      "pnl": -782.28,
      "r_multiple": -1.0,
      "risk_pct": 0.01,
      "regime": "aggressive_bull",
      "vix": 16.4
    },
    {
      "date": "2026-01-28",
      "symbol": "INTC",
      "signal": "long",
      "entry": 48.11,
      "shares": 708,
      "pnl": 456.13,
      "r_multiple": 0.58,
      "risk_pct": 0.01,
      "regime": "aggressive_bull",
      "vix": 16.4
    },
    {
      "date": "2026-01-29",
      "symbol": "INTC",
      "signal": "long",
      "entry": 48.27,
      "shares": 1544,
      "pnl": -792.07,
      "r_multiple": -1.0,
      "risk_pct": 0.01,
      "regime": "aggressive_bull",
      "vix": 16.9
    },
    {
      "date": "2026-01-30",
      "symbol": "CRM",
      "signal": "long",
      "entry": 214.53,
      "shares": 472,
      "pnl": -784.31,
      "r_multiple": -1.0,
      "risk_pct": 0.01,
      "regime": "aggressive_bull",
      "vix": 17.0
    }
  ]
}